llama_index/llms/huggingface_api/__init__.py
llama_index/llms/huggingface_api/base.py
llama_index_llms_huggingface_api-0.6.1.dist-info/METADATA
llama_index_llms_huggingface_api-0.6.1.dist-info/WHEEL
llama_index_llms_huggingface_api-0.6.1.dist-info/licenses/LICENSE
llama_index_llms_huggingface_api-0.6.1.dist-info/RECORD
