Metadata-Version: 2.4
Name: llama-index-llms-huggingface-api
Version: 0.6.1
Summary: llama-index llms huggingface api integration
Author-email: Your Name <you@example.com>
License-Expression: MIT
License-File: LICENSE
Requires-Python: <4.0,>=3.9
Requires-Dist: huggingface-hub>=0.31.0
Requires-Dist: llama-index-core<0.15,>=0.13.0
